<!DOCTYPE us-patent-grant SYSTEM "us-patent-grant-v44-2013-05-16.dtd" [ ]>
<us-patent-grant lang="EN" dtd-version="v4.4 2013-05-16" file="USD0697216-20140107.XML" status="PRODUCTION" id="us-patent-grant" country="US" date-produced="20131224" date-publ="20140107">
<us-bibliographic-data-grant>
<publication-reference>
<document-id>
<country>US</country>
<doc-number>D0697216</doc-number>
<kind>S1</kind>
<date>20140107</date>
</document-id>
</publication-reference>
<application-reference appl-type="design">
<document-id>
<country>US</country>
<doc-number>29386506</doc-number>
<date>20110301</date>
</document-id>
</application-reference>
<us-application-series-code>29</us-application-series-code>
<us-term-of-grant>
<length-of-grant>14</length-of-grant>
</us-term-of-grant>
<classification-locarno>
<edition>10</edition>
<main-classification>2404</main-classification>
</classification-locarno>
<classification-national>
<country>US</country>
<main-classification>D24189</main-classification>
</classification-national>
<invention-title id="d2e53">Adhesive bandage with decorated pad</invention-title>
<us-references-cited>
<us-citation>
<patcit num="00001">
<document-id>
<country>US</country>
<doc-number>2788003</doc-number>
<kind>A</kind>
<name>Morin</name>
<date>19570400</date>
</document-id>
</patcit>
<category>cited by applicant</category>
</us-citation>
<us-citation>
<patcit num="00002">
<document-id>
<country>US</country>
<doc-number>2896618</doc-number>
<kind>A</kind>
<name>Schaefer</name>
<date>19590700</date>
</document-id>
</patcit>
<category>cited by applicant</category>
</us-citation>
<us-citation>
<patcit num="00003">
<document-id>
<country>US</country>
<doc-number>3053252</doc-number>
<kind>A</kind>
<name>Wolf</name>
<date>19620900</date>
</document-id>
</patcit>
<category>cited by applicant</category>
</us-citation>
<us-citation>
<patcit num="00004">
<document-id>
<country>US</country>
<doc-number>3073304</doc-number>
<kind>A</kind>
<name>Schaar</name>
<date>19630100</date>
</document-id>
</patcit>
<category>cited by applicant</category>
</us-citation>
<us-citation>
<patcit num="00005">
<document-id>
<country>US</country>
<doc-number>3214502</doc-number>
<kind>A</kind>
<name>Schaar</name>
<date>19651000</date>
</document-id>
</patcit>
<category>cited by applicant</category>
</us-citation>
<us-citation>
<patcit num="00006">
<document-id>
<country>US</country>
<doc-number>3431911</doc-number>
<kind>A</kind>
<name>Meisel, Jr.</name>
<date>19690300</date>
</document-id>
</patcit>
<category>cited by applicant</category>
</us-citation>
<us-citation>
<patcit num="00007">
<document-id>
<country>US</country>
<doc-number>3494362</doc-number>
<kind>A</kind>
<name>Burgeni</name>
<date>19700200</date>
</document-id>
</patcit>
<category>cited by applicant</category>
</us-citation>
<us-citation>
<patcit num="00008">
<document-id>
<country>US</country>
<doc-number>3670731</doc-number>
<kind>A</kind>
<name>Harmon</name>
<date>19720600</date>
</document-id>
</patcit>
<category>cited by applicant</category>
</us-citation>
<us-citation>
<patcit num="00009">
<document-id>
<country>US</country>
<doc-number>3707430</doc-number>
<kind>A</kind>
<name>Costanza et al.</name>
<date>19721200</date>
</document-id>
</patcit>
<category>cited by applicant</category>
</us-citation>
<us-citation>
<patcit num="00010">
<document-id>
<country>US</country>
<doc-number>3731686</doc-number>
<kind>A</kind>
<name>Chatterjee</name>
<date>19730500</date>
</document-id>
</patcit>
<category>cited by applicant</category>
</us-citation>
<us-citation>
<patcit num="00011">
<document-id>
<country>US</country>
<doc-number>3858585</doc-number>
<kind>A</kind>
<name>Chatterjee</name>
<date>19750100</date>
</document-id>
</patcit>
<category>cited by applicant</category>
</us-citation>
<us-citation>
<patcit num="00012">
<document-id>
<country>US</country>
<doc-number>3903890</doc-number>
<kind>A</kind>
<name>Mesek et al.</name>
<date>19750900</date>
</document-id>
</patcit>
<category>cited by applicant</category>
</us-citation>
<us-citation>
<patcit num="00013">
<document-id>
<country>US</country>
<doc-number>3908659</doc-number>
<kind>A</kind>
<name>Wehrmeyer et al.</name>
<date>19750900</date>
</document-id>
</patcit>
<category>cited by applicant</category>
</us-citation>
<us-citation>
<patcit num="00014">
<document-id>
<country>US</country>
<doc-number>4145464</doc-number>
<kind>A</kind>
<name>McConnell et al.</name>
<date>19790300</date>
</document-id>
</patcit>
<category>cited by applicant</category>
</us-citation>
<us-citation>
<patcit num="00015">
<document-id>
<country>US</country>
<doc-number>4259387</doc-number>
<kind>A</kind>
<name>Mesek</name>
<date>19810300</date>
</document-id>
</patcit>
<category>cited by applicant</category>
</us-citation>
<us-citation>
<patcit num="00016">
<document-id>
<country>US</country>
<doc-number>4423101</doc-number>
<kind>A</kind>
<name>Willstead</name>
<date>19831200</date>
</document-id>
</patcit>
<category>cited by applicant</category>
</us-citation>
<us-citation>
<patcit num="00017">
<document-id>
<country>US</country>
<doc-number>4616644</doc-number>
<kind>A</kind>
<name>Saferstein et al.</name>
<date>19861000</date>
</document-id>
</patcit>
<category>cited by applicant</category>
</us-citation>
<us-citation>
<patcit num="00018">
<document-id>
<country>US</country>
<doc-number>D288363</doc-number>
<kind>S</kind>
<name>Wallstrom</name>
<date>19870200</date>
</document-id>
</patcit>
<category>cited by examiner</category>
<classification-national><country>US</country><main-classification>D24125</main-classification></classification-national>
</us-citation>
<us-citation>
<patcit num="00019">
<document-id>
<country>US</country>
<doc-number>4781710</doc-number>
<kind>A</kind>
<name>Megison et al.</name>
<date>19881100</date>
</document-id>
</patcit>
<category>cited by applicant</category>
</us-citation>
<us-citation>
<patcit num="00020">
<document-id>
<country>US</country>
<doc-number>5051259</doc-number>
<kind>A</kind>
<name>Olsen et al.</name>
<date>19910900</date>
</document-id>
</patcit>
<category>cited by applicant</category>
</us-citation>
<us-citation>
<patcit num="00021">
<document-id>
<country>US</country>
<doc-number>5158555</doc-number>
<kind>A</kind>
<name>Porzilli</name>
<date>19921000</date>
</document-id>
</patcit>
<category>cited by applicant</category>
</us-citation>
<us-citation>
<patcit num="00022">
<document-id>
<country>US</country>
<doc-number>5250043</doc-number>
<kind>A</kind>
<name>Castellana et al.</name>
<date>19931000</date>
</document-id>
</patcit>
<category>cited by applicant</category>
</us-citation>
<us-citation>
<patcit num="00023">
<document-id>
<country>US</country>
<doc-number>5328450</doc-number>
<kind>A</kind>
<name>Smith et al.</name>
<date>19940700</date>
</document-id>
</patcit>
<category>cited by applicant</category>
</us-citation>
<us-citation>
<patcit num="00024">
<document-id>
<country>US</country>
<doc-number>5423736</doc-number>
<kind>A</kind>
<name>Cartmell et al.</name>
<date>19950600</date>
</document-id>
</patcit>
<category>cited by applicant</category>
</us-citation>
<us-citation>
<patcit num="00025">
<document-id>
<country>US</country>
<doc-number>5429589</doc-number>
<kind>A</kind>
<name>Cartmell et al.</name>
<date>19950700</date>
</document-id>
</patcit>
<category>cited by examiner</category>
<classification-national><country>US</country><main-classification>602 42</main-classification></classification-national>
</us-citation>
<us-citation>
<patcit num="00026">
<document-id>
<country>US</country>
<doc-number>D383211</doc-number>
<kind>S</kind>
<name>Dunshee et al.</name>
<date>19970900</date>
</document-id>
</patcit>
<category>cited by examiner</category>
<classification-national><country>US</country><main-classification>D24189</main-classification></classification-national>
</us-citation>
<us-citation>
<patcit num="00027">
<document-id>
<country>US</country>
<doc-number>5681301</doc-number>
<kind>A</kind>
<name>Yang et al.</name>
<date>19971000</date>
</document-id>
</patcit>
<category>cited by applicant</category>
</us-citation>
<us-citation>
<patcit num="00028">
<document-id>
<country>US</country>
<doc-number>D387169</doc-number>
<kind>S</kind>
<name>Dunshee et al.</name>
<date>19971200</date>
</document-id>
</patcit>
<category>cited by examiner</category>
<classification-national><country>US</country><main-classification>D24189</main-classification></classification-national>
</us-citation>
<us-citation>
<patcit num="00029">
<document-id>
<country>US</country>
<doc-number>D389244</doc-number>
<kind>S</kind>
<name>Dunshee et al.</name>
<date>19980100</date>
</document-id>
</patcit>
<category>cited by examiner</category>
<classification-national><country>US</country><main-classification>D24189</main-classification></classification-national>
</us-citation>
<us-citation>
<patcit num="00030">
<document-id>
<country>US</country>
<doc-number>D391639</doc-number>
<kind>S</kind>
<name>Dunshee et al.</name>
<date>19980300</date>
</document-id>
</patcit>
<category>cited by examiner</category>
<classification-national><country>US</country><main-classification>D24189</main-classification></classification-national>
</us-citation>
<us-citation>
<patcit num="00031">
<document-id>
<country>US</country>
<doc-number>5782787</doc-number>
<kind>A</kind>
<name>Webster</name>
<date>19980700</date>
</document-id>
</patcit>
<category>cited by applicant</category>
</us-citation>
<us-citation>
<patcit num="00032">
<document-id>
<country>US</country>
<doc-number>D402371</doc-number>
<kind>S</kind>
<name>Haynes et al.</name>
<date>19981200</date>
</document-id>
</patcit>
<category>cited by examiner</category>
<classification-national><country>US</country><main-classification>D24189</main-classification></classification-national>
</us-citation>
<us-citation>
<patcit num="00033">
<document-id>
<country>US</country>
<doc-number>D404136</doc-number>
<kind>S</kind>
<name>Dunshee et al.</name>
<date>19990100</date>
</document-id>
</patcit>
<category>cited by examiner</category>
<classification-national><country>US</country><main-classification>D24189</main-classification></classification-national>
</us-citation>
<us-citation>
<patcit num="00034">
<document-id>
<country>US</country>
<doc-number>D407160</doc-number>
<kind>S</kind>
<name>Dunshee et al.</name>
<date>19990300</date>
</document-id>
</patcit>
<category>cited by examiner</category>
<classification-national><country>US</country><main-classification>D24189</main-classification></classification-national>
</us-citation>
<us-citation>
<patcit num="00035">
<document-id>
<country>US</country>
<doc-number>5954679</doc-number>
<kind>A</kind>
<name>Baranitsky</name>
<date>19990900</date>
</document-id>
</patcit>
<category>cited by applicant</category>
</us-citation>
<us-citation>
<patcit num="00036">
<document-id>
<country>US</country>
<doc-number>5990377</doc-number>
<kind>A</kind>
<name>Chen et al.</name>
<date>19991100</date>
</document-id>
</patcit>
<category>cited by applicant</category>
</us-citation>
<us-citation>
<patcit num="00037">
<document-id>
<country>US</country>
<doc-number>5998032</doc-number>
<kind>A</kind>
<name>Hansen et al.</name>
<date>19991200</date>
</document-id>
</patcit>
<category>cited by applicant</category>
</us-citation>
<us-citation>
<patcit num="00038">
<document-id>
<country>US</country>
<doc-number>D424699</doc-number>
<kind>S</kind>
<name>Allen</name>
<date>20000500</date>
</document-id>
</patcit>
<category>cited by examiner</category>
<classification-national><country>US</country><main-classification>D24189</main-classification></classification-national>
</us-citation>
<us-citation>
<patcit num="00039">
<document-id>
<country>US</country>
<doc-number>6171648</doc-number>
<kind>B1</kind>
<name>Himmelsbach et al.</name>
<date>20010100</date>
</document-id>
</patcit>
<category>cited by applicant</category>
</us-citation>
<us-citation>
<patcit num="00040">
<document-id>
<country>US</country>
<doc-number>6245961</doc-number>
<kind>B1</kind>
<name>Roxendal et al.</name>
<date>20010600</date>
</document-id>
</patcit>
<category>cited by applicant</category>
</us-citation>
<us-citation>
<patcit num="00041">
<document-id>
<country>US</country>
<doc-number>6384294</doc-number>
<kind>B1</kind>
<name>Levin</name>
<date>20020500</date>
</document-id>
</patcit>
<category>cited by applicant</category>
</us-citation>
<us-citation>
<patcit num="00042">
<document-id>
<country>US</country>
<doc-number>6395395</doc-number>
<kind>B1</kind>
<name>Hansen et al.</name>
<date>20020500</date>
</document-id>
</patcit>
<category>cited by applicant</category>
</us-citation>
<us-citation>
<patcit num="00043">
<document-id>
<country>US</country>
<doc-number>6395957</doc-number>
<kind>B1</kind>
<name>Chen et al.</name>
<date>20020500</date>
</document-id>
</patcit>
<category>cited by applicant</category>
</us-citation>
<us-citation>
<patcit num="00044">
<document-id>
<country>US</country>
<doc-number>6420622</doc-number>
<kind>B1</kind>
<name>Johnston et al.</name>
<date>20020700</date>
</document-id>
</patcit>
<category>cited by applicant</category>
</us-citation>
<us-citation>
<patcit num="00045">
<document-id>
<country>US</country>
<doc-number>6566575</doc-number>
<kind>B1</kind>
<name>Stickels et al.</name>
<date>20030500</date>
</document-id>
</patcit>
<category>cited by applicant</category>
</us-citation>
<us-citation>
<patcit num="00046">
<document-id>
<country>US</country>
<doc-number>6747186</doc-number>
<kind>B2</kind>
<name>Shimizu</name>
<date>20040600</date>
</document-id>
</patcit>
<category>cited by applicant</category>
</us-citation>
<us-citation>
<patcit num="00047">
<document-id>
<country>US</country>
<doc-number>6897348</doc-number>
<kind>B2</kind>
<name>Malik</name>
<date>20050500</date>
</document-id>
</patcit>
<category>cited by applicant</category>
</us-citation>
<us-citation>
<patcit num="00048">
<document-id>
<country>US</country>
<doc-number>D511006</doc-number>
<kind>S</kind>
<name>Dodd et al.</name>
<date>20051000</date>
</document-id>
</patcit>
<category>cited by examiner</category>
<classification-national><country>US</country><main-classification>D24189</main-classification></classification-national>
</us-citation>
<us-citation>
<patcit num="00049">
<document-id>
<country>US</country>
<doc-number>6967261</doc-number>
<kind>B1</kind>
<name>Soerens et al.</name>
<date>20051100</date>
</document-id>
</patcit>
<category>cited by applicant</category>
</us-citation>
<us-citation>
<patcit num="00050">
<document-id>
<country>US</country>
<doc-number>7105716</doc-number>
<kind>B2</kind>
<name>Baratian et al.</name>
<date>20060900</date>
</document-id>
</patcit>
<category>cited by applicant</category>
</us-citation>
<us-citation>
<patcit num="00051">
<document-id>
<country>US</country>
<doc-number>7154017</doc-number>
<kind>B2</kind>
<name>Sigurjonsson et al.</name>
<date>20061200</date>
</document-id>
</patcit>
<category>cited by applicant</category>
</us-citation>
<us-citation>
<patcit num="00052">
<document-id>
<country>US</country>
<doc-number>7214847</doc-number>
<kind>B1</kind>
<name>Flick</name>
<date>20070500</date>
</document-id>
</patcit>
<category>cited by applicant</category>
</us-citation>
<us-citation>
<patcit num="00053">
<document-id>
<country>US</country>
<doc-number>7220889</doc-number>
<kind>B2</kind>
<name>Sigurjonsson et al.</name>
<date>20070500</date>
</document-id>
</patcit>
<category>cited by applicant</category>
</us-citation>
<us-citation>
<patcit num="00054">
<document-id>
<country>US</country>
<doc-number>D545970</doc-number>
<kind>S</kind>
<name>Eknoian et al.</name>
<date>20070700</date>
</document-id>
</patcit>
<category>cited by applicant</category>
</us-citation>
<us-citation>
<patcit num="00055">
<document-id>
<country>US</country>
<doc-number>7238849</doc-number>
<kind>B2</kind>
<name>Goldberg et al.</name>
<date>20070700</date>
</document-id>
</patcit>
<category>cited by applicant</category>
</us-citation>
<us-citation>
<patcit num="00056">
<document-id>
<country>US</country>
<doc-number>7270721</doc-number>
<kind>B2</kind>
<name>Hilfenhaus et al.</name>
<date>20070900</date>
</document-id>
</patcit>
<category>cited by applicant</category>
</us-citation>
<us-citation>
<patcit num="00057">
<document-id>
<country>US</country>
<doc-number>7291762</doc-number>
<kind>B2</kind>
<name>Flick</name>
<date>20071100</date>
</document-id>
</patcit>
<category>cited by applicant</category>
</us-citation>
<us-citation>
<patcit num="00058">
<document-id>
<country>US</country>
<doc-number>7304202</doc-number>
<kind>B2</kind>
<name>Sigurjonsson et al.</name>
<date>20071200</date>
</document-id>
</patcit>
<category>cited by applicant</category>
</us-citation>
<us-citation>
<patcit num="00059">
<document-id>
<country>US</country>
<doc-number>7329792</doc-number>
<kind>B2</kind>
<name>Buckman et al.</name>
<date>20080200</date>
</document-id>
</patcit>
<category>cited by applicant</category>
</us-citation>
<us-citation>
<patcit num="00060">
<document-id>
<country>US</country>
<doc-number>7335612</doc-number>
<kind>B2</kind>
<name>Kim</name>
<date>20080200</date>
</document-id>
</patcit>
<category>cited by applicant</category>
</us-citation>
<us-citation>
<patcit num="00061">
<document-id>
<country>US</country>
<doc-number>D570421</doc-number>
<kind>S</kind>
<name>Andersson</name>
<date>20080600</date>
</document-id>
</patcit>
<category>cited by examiner</category>
<classification-national><country>US</country><main-classification>D21376</main-classification></classification-national>
</us-citation>
<us-citation>
<patcit num="00062">
<document-id>
<country>US</country>
<doc-number>7396975</doc-number>
<kind>B2</kind>
<name>Sigurjonsson et al.</name>
<date>20080700</date>
</document-id>
</patcit>
<category>cited by applicant</category>
</us-citation>
<us-citation>
<patcit num="00063">
<document-id>
<country>US</country>
<doc-number>7468471</doc-number>
<kind>B2</kind>
<name>Sigurjonsson et al.</name>
<date>20081200</date>
</document-id>
</patcit>
<category>cited by applicant</category>
</us-citation>
<us-citation>
<patcit num="00064">
<document-id>
<country>US</country>
<doc-number>D611156</doc-number>
<kind>S</kind>
<name>Dunshee</name>
<date>20100300</date>
</document-id>
</patcit>
<category>cited by examiner</category>
<classification-national><country>US</country><main-classification>D24189</main-classification></classification-national>
</us-citation>
<us-citation>
<patcit num="00065">
<document-id>
<country>US</country>
<doc-number>7811021</doc-number>
<kind>B2</kind>
<name>Gueret</name>
<date>20101000</date>
</document-id>
</patcit>
<category>cited by applicant</category>
</us-citation>
<us-citation>
<patcit num="00066">
<document-id>
<country>US</country>
<doc-number>D646789</doc-number>
<kind>S</kind>
<name>Barth</name>
<date>20111000</date>
</document-id>
</patcit>
<category>cited by examiner</category>
<classification-national><country>US</country><main-classification>D24189</main-classification></classification-national>
</us-citation>
<us-citation>
<patcit num="00067">
<document-id>
<country>US</country>
<doc-number>D648439</doc-number>
<kind>S</kind>
<name>Greener et al.</name>
<date>20111100</date>
</document-id>
</patcit>
<category>cited by examiner</category>
<classification-national><country>US</country><main-classification>D24189</main-classification></classification-national>
</us-citation>
<us-citation>
<patcit num="00068">
<document-id>
<country>US</country>
<doc-number>2003/0208175</doc-number>
<kind>A1</kind>
<name>Gross et al.</name>
<date>20031100</date>
</document-id>
</patcit>
<category>cited by applicant</category>
</us-citation>
<us-citation>
<patcit num="00069">
<document-id>
<country>US</country>
<doc-number>2004/0049145</doc-number>
<kind>A1</kind>
<name>Flick</name>
<date>20040300</date>
</document-id>
</patcit>
<category>cited by applicant</category>
</us-citation>
<us-citation>
<patcit num="00070">
<document-id>
<country>US</country>
<doc-number>2004/0127834</doc-number>
<kind>A1</kind>
<name>Sigurjonsson et al.</name>
<date>20040700</date>
</document-id>
</patcit>
<category>cited by applicant</category>
</us-citation>
<us-citation>
<patcit num="00071">
<document-id>
<country>US</country>
<doc-number>2004/0127835</doc-number>
<kind>A1</kind>
<name>Sigurjonsson et al.</name>
<date>20040700</date>
</document-id>
</patcit>
<category>cited by applicant</category>
</us-citation>
<us-citation>
<patcit num="00072">
<document-id>
<country>US</country>
<doc-number>2004/0127836</doc-number>
<kind>A1</kind>
<name>Sigurjonsson et al.</name>
<date>20040700</date>
</document-id>
</patcit>
<category>cited by applicant</category>
</us-citation>
<us-citation>
<patcit num="00073">
<document-id>
<country>US</country>
<doc-number>2004/0127837</doc-number>
<kind>A1</kind>
<name>Sigurjonsson</name>
<date>20040700</date>
</document-id>
</patcit>
<category>cited by applicant</category>
</us-citation>
<us-citation>
<patcit num="00074">
<document-id>
<country>US</country>
<doc-number>2004/0127839</doc-number>
<kind>A1</kind>
<name>Sigurjonsson et al.</name>
<date>20040700</date>
</document-id>
</patcit>
<category>cited by applicant</category>
</us-citation>
<us-citation>
<patcit num="00075">
<document-id>
<country>US</country>
<doc-number>2004/0133143</doc-number>
<kind>A1</kind>
<name>Burton et al.</name>
<date>20040700</date>
</document-id>
</patcit>
<category>cited by applicant</category>
</us-citation>
<us-citation>
<patcit num="00076">
<document-id>
<country>US</country>
<doc-number>2004/0138604</doc-number>
<kind>A1</kind>
<name>Sigurjonsson et al.</name>
<date>20040700</date>
</document-id>
</patcit>
<category>cited by applicant</category>
</us-citation>
<us-citation>
<patcit num="00077">
<document-id>
<country>US</country>
<doc-number>2004/0138605</doc-number>
<kind>A1</kind>
<name>Sigurjonsson et al.</name>
<date>20040700</date>
</document-id>
</patcit>
<category>cited by applicant</category>
</us-citation>
<us-citation>
<patcit num="00078">
<document-id>
<country>US</country>
<doc-number>2005/0165445</doc-number>
<kind>A1</kind>
<name>Buckman et al.</name>
<date>20050700</date>
</document-id>
</patcit>
<category>cited by applicant</category>
</us-citation>
<us-citation>
<patcit num="00079">
<document-id>
<country>US</country>
<doc-number>2007/0129697</doc-number>
<kind>A1</kind>
<name>Soerens et al.</name>
<date>20070600</date>
</document-id>
</patcit>
<category>cited by applicant</category>
</us-citation>
<us-citation>
<patcit num="00080">
<document-id>
<country>US</country>
<doc-number>2007/0142803</doc-number>
<kind>A1</kind>
<name>Soerens et al.</name>
<date>20070600</date>
</document-id>
</patcit>
<category>cited by applicant</category>
</us-citation>
<us-citation>
<patcit num="00081">
<document-id>
<country>US</country>
<doc-number>2008/0033506</doc-number>
<kind>A1</kind>
<name>Flick</name>
<date>20080200</date>
</document-id>
</patcit>
<category>cited by applicant</category>
</us-citation>
<us-citation>
<patcit num="00082">
<document-id>
<country>US</country>
<doc-number>2008/0039763</doc-number>
<kind>A1</kind>
<name>Sigurjonsson et al.</name>
<date>20080200</date>
</document-id>
</patcit>
<category>cited by applicant</category>
</us-citation>
<us-citation>
<patcit num="00083">
<document-id>
<country>US</country>
<doc-number>2008/0076844</doc-number>
<kind>A1</kind>
<name>Van Sumeren et al.</name>
<date>20080300</date>
</document-id>
</patcit>
<category>cited by applicant</category>
</us-citation>
<us-citation>
<patcit num="00084">
<document-id>
<country>US</country>
<doc-number>2008/0119773</doc-number>
<kind>A1</kind>
<name>Flick</name>
<date>20080500</date>
</document-id>
</patcit>
<category>cited by applicant</category>
</us-citation>
<us-citation>
<patcit num="00085">
<document-id>
<country>US</country>
<doc-number>2008/0255493</doc-number>
<kind>A1</kind>
<name>Sigurjonsson et al.</name>
<date>20081000</date>
</document-id>
</patcit>
<category>cited by applicant</category>
</us-citation>
<us-citation>
<patcit num="00086">
<document-id>
<country>US</country>
<doc-number>2010/0179463</doc-number>
<kind>A1</kind>
<name>Greener et al.</name>
<date>20100700</date>
</document-id>
</patcit>
<category>cited by applicant</category>
</us-citation>
<us-citation>
<patcit num="00087">
<document-id>
<country>CA</country>
<doc-number>2321418</doc-number>
<date>19920700</date>
</document-id>
</patcit>
<category>cited by applicant</category>
</us-citation>
<us-citation>
<patcit num="00088">
<document-id>
<country>WO</country>
<doc-number>2010147535</doc-number>
<date>20101200</date>
</document-id>
</patcit>
<category>cited by applicant</category>
</us-citation>
</us-references-cited>
<number-of-claims>1</number-of-claims>
<us-exemplary-claim>1</us-exemplary-claim>
<us-field-of-classification-search>
<classification-national>
<country>US</country>
<main-classification>D20 10- 11</main-classification>
<additional-info>unstructured</additional-info>
</classification-national>
<classification-national>
<country>US</country>
<main-classification>D20 23</main-classification>
</classification-national>
<classification-national>
<country>US</country>
<main-classification>D20 35</main-classification>
</classification-national>
<classification-national>
<country>US</country>
<main-classification>D20 42</main-classification>
</classification-national>
<classification-national>
<country>US</country>
<main-classification>D24189</main-classification>
</classification-national>
<classification-national>
<country>US</country>
<main-classification>602 41- 48</main-classification>
<additional-info>unstructured</additional-info>
</classification-national>
<classification-national>
<country>US</country>
<main-classification>602 54- 55</main-classification>
<additional-info>unstructured</additional-info>
</classification-national>
<classification-national>
<country>US</country>
<main-classification>602 58</main-classification>
</classification-national>
</us-field-of-classification-search>
<figures>
<number-of-drawing-sheets>5</number-of-drawing-sheets>
<number-of-figures>15</number-of-figures>
</figures>
<us-related-documents>
<continuation-in-part>
<relation>
<parent-doc>
<document-id>
<country>US</country>
<doc-number>13036499</doc-number>
<date>20110228</date>
</document-id>
<parent-status>PENDING</parent-status>
</parent-doc>
<child-doc>
<document-id>
<country>US</country>
<doc-number>29386506</doc-number>
</document-id>
</child-doc>
</relation>
</continuation-in-part>
<continuation-in-part>
<relation>
<parent-doc>
<document-id>
<country>US</country>
<doc-number>13036471</doc-number>
<date>20110228</date>
</document-id>
<parent-status>PENDING</parent-status>
</parent-doc>
<child-doc>
<document-id>
<country>US</country>
<doc-number>13036499</doc-number>
</document-id>
</child-doc>
</relation>
</continuation-in-part>
</us-related-documents>
<us-parties>
<us-applicants>
<us-applicant sequence="001" app-type="applicant" designation="us-only">
<addressbook>
<last-name>Chan</last-name>
<first-name>Jennifer Wing-Yee</first-name>
<address>
<city>Belle Mead</city>
<state>NJ</state>
<country>US</country>
</address>
</addressbook>
<residence>
<country>US</country>
</residence>
</us-applicant>
<us-applicant sequence="002" app-type="applicant" designation="us-only">
<addressbook>
<last-name>Eknoian</last-name>
<first-name>Michael William</first-name>
<address>
<city>Warren</city>
<state>NJ</state>
<country>US</country>
</address>
</addressbook>
<residence>
<country>US</country>
</residence>
</us-applicant>
<us-applicant sequence="003" app-type="applicant" designation="us-only">
<addressbook>
<last-name>Petersack</last-name>
<first-name>Vincent John</first-name>
<address>
<city>Eastampton</city>
<state>NJ</state>
<country>US</country>
</address>
</addressbook>
<residence>
<country>US</country>
</residence>
</us-applicant>
<us-applicant sequence="004" app-type="applicant" designation="us-only">
<addressbook>
<last-name>Rizzo</last-name>
<first-name>Carmine Michael</first-name>
<address>
<city>Cliffwood Beach</city>
<state>NJ</state>
<country>US</country>
</address>
</addressbook>
<residence>
<country>US</country>
</residence>
</us-applicant>
<us-applicant sequence="005" app-type="applicant" designation="us-only">
<addressbook>
<last-name>Taylor</last-name>
<first-name>Karin</first-name>
<address>
<city>New York</city>
<state>NY</state>
<country>US</country>
</address>
</addressbook>
<residence>
<country>US</country>
</residence>
</us-applicant>
</us-applicants>
<inventors>
<inventor sequence="001" designation="us-only">
<addressbook>
<last-name>Chan</last-name>
<first-name>Jennifer Wing-Yee</first-name>
<address>
<city>Belle Mead</city>
<state>NJ</state>
<country>US</country>
</address>
</addressbook>
</inventor>
<inventor sequence="002" designation="us-only">
<addressbook>
<last-name>Eknoian</last-name>
<first-name>Michael William</first-name>
<address>
<city>Warren</city>
<state>NJ</state>
<country>US</country>
</address>
</addressbook>
</inventor>
<inventor sequence="003" designation="us-only">
<addressbook>
<last-name>Petersack</last-name>
<first-name>Vincent John</first-name>
<address>
<city>Eastampton</city>
<state>NJ</state>
<country>US</country>
</address>
</addressbook>
</inventor>
<inventor sequence="004" designation="us-only">
<addressbook>
<last-name>Rizzo</last-name>
<first-name>Carmine Michael</first-name>
<address>
<city>Cliffwood Beach</city>
<state>NJ</state>
<country>US</country>
</address>
</addressbook>
</inventor>
<inventor sequence="005" designation="us-only">
<addressbook>
<last-name>Taylor</last-name>
<first-name>Karin</first-name>
<address>
<city>New York</city>
<state>NY</state>
<country>US</country>
</address>
</addressbook>
</inventor>
</inventors>
</us-parties>
<assignees>
<assignee>
<addressbook>
<orgname>Johnson &#x26; Johnson Consumer Companies, Inc.</orgname>
<role>02</role>
<address>
<city>Skillman</city>
<state>NJ</state>
<country>US</country>
</address>
</addressbook>
</assignee>
</assignees>
<examiners>
<primary-examiner>
<last-name>Nelson</last-name>
<first-name>T. Chase</first-name>
<department>2914</department>
</primary-examiner>
<assistant-examiner>
<last-name>Wilson</last-name>
<first-name>Michelle E</first-name>
</assistant-examiner>
</examiners>
</us-bibliographic-data-grant>
<drawings id="DRAWINGS">
<figure id="Fig-EMI-D00000" num="00000">
<img id="EMI-D00000" he="47.84mm" wi="116.42mm" file="USD0697216-20140107-D00000.TIF" alt="embedded image" img-content="drawing" img-format="tif"/>
</figure>
<figure id="Fig-EMI-D00001" num="00001">
<img id="EMI-D00001" he="181.02mm" wi="149.61mm" file="USD0697216-20140107-D00001.TIF" alt="embedded image" img-content="drawing" img-format="tif"/>
</figure>
<figure id="Fig-EMI-D00002" num="00002">
<img id="EMI-D00002" he="179.75mm" wi="148.93mm" file="USD0697216-20140107-D00002.TIF" alt="embedded image" img-content="drawing" img-format="tif"/>
</figure>
<figure id="Fig-EMI-D00003" num="00003">
<img id="EMI-D00003" he="180.42mm" wi="145.54mm" file="USD0697216-20140107-D00003.TIF" alt="embedded image" img-content="drawing" img-format="tif"/>
</figure>
<figure id="Fig-EMI-D00004" num="00004">
<img id="EMI-D00004" he="179.75mm" wi="148.67mm" file="USD0697216-20140107-D00004.TIF" alt="embedded image" img-content="drawing" img-format="tif"/>
</figure>
<figure id="Fig-EMI-D00005" num="00005">
<img id="EMI-D00005" he="180.09mm" wi="146.13mm" file="USD0697216-20140107-D00005.TIF" alt="embedded image" img-content="drawing" img-format="tif"/>
</figure>
</drawings>
<description id="description">
<?brief-description-of-drawings description="Brief Description of Drawings" end="lead"?>
<description-of-drawings>
<p id="p-0001" num="0001"><figref idref="DRAWINGS">FIG. 1</figref> is a plan view of an adhesive bandage with a decorated absorbent pad showing my new design;</p>
<p id="p-0002" num="0002"><figref idref="DRAWINGS">FIG. 2</figref> is a side elevational view thereof, the opposite side elevational view being a mirror image;</p>
<p id="p-0003" num="0003"><figref idref="DRAWINGS">FIG. 3</figref> is an end elevational view thereof, the opposite end elevational view being a mirror image;</p>
<p id="p-0004" num="0004"><figref idref="DRAWINGS">FIG. 4</figref> is a plan view of a second embodiment of a decorated absorbent pad showing my new design;</p>
<p id="p-0005" num="0005"><figref idref="DRAWINGS">FIG. 5</figref> is a side elevational view thereof, the opposite side elevational view being a mirror image;</p>
<p id="p-0006" num="0006"><figref idref="DRAWINGS">FIG. 6</figref> is an end elevational view thereof, the opposite end elevational view being a mirror image;</p>
<p id="p-0007" num="0007"><figref idref="DRAWINGS">FIG. 7</figref> is a plan view of an adhesive bandage with a third embodiment of a decorated absorbent pad showing my new design;</p>
<p id="p-0008" num="0008"><figref idref="DRAWINGS">FIG. 8</figref> is a side elevational view thereof, the opposite side elevational view being a mirror image;</p>
<p id="p-0009" num="0009"><figref idref="DRAWINGS">FIG. 9</figref> is an end elevational view thereof, the opposite end elevational view being a mirror image;</p>
<p id="p-0010" num="0010"><figref idref="DRAWINGS">FIG. 10</figref> is a plan view of an adhesive bandage with a fourth embodiment of a decorated absorbent pad showing my new design;</p>
<p id="p-0011" num="0011"><figref idref="DRAWINGS">FIG. 11</figref> is a side elevational view thereof, the opposite side elevational view being a mirror image;</p>
<p id="p-0012" num="0012"><figref idref="DRAWINGS">FIG. 12</figref> is an end elevational view thereof, the opposite end elevational view being a mirror image;</p>
<p id="p-0013" num="0013"><figref idref="DRAWINGS">FIG. 13</figref> is a plan view of an adhesive bandage with a fifth embodiment of a decorated absorbent pad showing my new design;</p>
<p id="p-0014" num="0014"><figref idref="DRAWINGS">FIG. 14</figref> is a side elevational view thereof, the opposite side elevational view being a mirror image; and,</p>
<p id="p-0015" num="0015"><figref idref="DRAWINGS">FIG. 15</figref> is an end elevational view thereof, the opposite end elevational view being a mirror image.</p>
<p id="p-0016" num="0016">The broken line showing of the backing of the adhesive bandage is included for the purpose of illustrating environment and forms no part of the claimed design.</p>
<p id="p-0017" num="0017">The dashed lines are representative of boundaries between claimed and unclaimed subject matter in the embodiments of <figref idref="DRAWINGS">FIGS. 1-15</figref>. The jagged or wavy dot-dash lines in the unclaimed areas of the absorbent pad on either side of the claimed area of the absorbent pad in the embodiments of <figref idref="DRAWINGS">FIGS. 1-15</figref> represent any portion of the article beyond what is shown forms no part of the claimed design.</p>
<p id="p-0018" num="0018">The embodiment of <figref idref="DRAWINGS">FIGS. 7-9</figref> illustrates a pattern that is similar to the pattern of <figref idref="DRAWINGS">FIGS. 1-3</figref> but which is approximately two degrees off from vertical or from being parallel to the side edges of the absorbent pad. However, it will be appreciated that the orientation of the repeating pattern of the decorated absorbent pads of all embodiments of the present invention is intended to not be limited to be exactly vertical or parallel to the side edges of the absorbent pad.</p>
</description-of-drawings>
<?brief-description-of-drawings description="Brief Description of Drawings" end="tail"?>
</description>
<us-claim-statement>CLAIM</us-claim-statement>
<claims id="claims">
<claim id="CLM-00001" num="00001">
<claim-text>We claim the ornamental design for an adhesive bandage with decorated pad, as shown and described.</claim-text>
</claim>
</claims>
</us-patent-grant>
